{
 "property": "media",
 "blocks": [
  {
   "title": "Comentários",
   "type": "text",
   "property": "details",
   "placeholder": "Digite seus comentários"
  },
  {
   "title": "Nota",
   "type": "radio-h",
   "comments": [
    {
     "title": "1 |",
     "property": "grade",
     "value": "1"
    },
    {
     "title": "2 |",
     "property": "grade",
     "value": "2"
    },
    {
     "title": "3 |",
     "property": "grade",
     "value": "3"
    },
    {
     "title": "4 |",
     "property": "grade",
     "value": "4"
    },
    {
     "title": "5 |",
     "property": "grade",
     "value": "5"
    }
   ]
  }
 ],
 "contexts": {
  "AB-QSD": {
   "title": "Vídeo - QSD",
   "property": "media",
   "blocks": [
    {
     "title": "Ganho",
     "type": "radio",
     "comments": [
      {
       "title": "1. insuficiente",
       "property": "gain",
       "value": "insufficient"
      },
      {
       "title": "2. apropriado",
       "property": "gain",
       "value": "appropriate"
      },
      {
       "title": "3. excessivo",
       "property": "gain",
       "value": "excessive"
      }
     ]
    },
    {
     "title": "Profundidade",
     "type": "radio",
     "comments": [
      {
       "title": "1. insuficiente",
       "property": "depth",
       "value": "insufficient"
      },
      {
       "title": "2. apropriado",
       "property": "depth",
       "value": "appropriate"
      },
      {
       "title": "3. excessivo",
       "property": "depth",
       "value": "excessive"
      }
     ]
    },
    {
     "title": "Nota",
     "type": "radio-h",
     "comments": [
      {
       "title": "1 |",
       "property": "grade",
       "value": "1"
      },
      {
       "title": "2 |",
       "property": "grade",
       "value": "2"
      },
      {
       "title": "3 |",
       "property": "grade",
       "value": "3"
      },
      {
       "title": "4 |",
       "property": "grade",
       "value": "4"
      },
      {
       "title": "5 |",
       "property": "grade",
       "value": "5"
      }
     ]
    },
    {
     "title": "Referências anatómicas/qualidade",
     "type": "checkbox",
     "comments": [
      {
       "title": "Diafragma ausente",
       "property": "diaphragm",
       "value": "not_present"
      },
      {
       "title": "Espaço de Morrison/hepatorenal ausente",
       "property": "morrison_hepatorenal_space",
       "value": "not_present"
      },
      {
       "title": "Pólo inferior do rim direito ausente",
       "property": "lower_pole_right_kidney",
       "value": "not_present"
      }
     ]
    }
   ]
  },
  "AB-QSE": {
   "title": "Vídeo - QSE",
   "property": "media",
   "blocks": [
    {
     "title": "Ganho",
     "type": "radio",
     "comments": [
      {
       "title": "1. insuficiente",
       "property": "gain",
       "value": "insufficient"
      },
      {
       "title": "2. apropriado",
       "property": "gain",
       "value": "appropriate"
      },
      {
       "title": "3. excessivo",
       "property": "gain",
       "value": "excessive"
      }
     ]
    },
    {
     "title": "Profundidade",
     "type": "radio",
     "comments": [
      {
       "title": "1. insuficiente",
       "property": "depth",
       "value": "insufficient"
      },
      {
       "title": "2. apropriado",
       "property": "depth",
       "value": "appropriate"
      },
      {
       "title": "3. excessivo",
       "property": "depth",
       "value": "excessive"
      }
     ]
    },
    {
     "title": "Nota",
     "type": "radio-h",
     "comments": [
      {
       "title": "1 |",
       "property": "grade",
       "value": "1"
      },
      {
       "title": "2 |",
       "property": "grade",
       "value": "2"
      },
      {
       "title": "3 |",
       "property": "grade",
       "value": "3"
      },
      {
       "title": "4 |",
       "property": "grade",
       "value": "4"
      },
      {
       "title": "5 |",
       "property": "grade",
       "value": "5"
      }
     ]
    },
    {
     "title": "Referências anatómicas/qualidade",
     "type": "checkbox",
     "comments": [
      {
       "title": "Diafragma ausente",
       "property": "diaphragm",
       "value": "not_present"
      },
      {
       "title": "Espaço espleno renal ausente",
       "property": "spenorenal_recess",
       "value": "not_present"
      },
      {
       "title": "Ponta posterior do baço ausente",
       "property": "posterior_tip_spleen",
       "value": "not_present"
      },
      {
       "title": "Pólo inferior do rim esquerdo ausente",
       "property": "lower_pole_left_kidney",
       "value": "not_present"
      }
     ]
    }
   ]
  },
  "AB-PT": {
   "title": "Vídeo - Pelve transversal",
   "property": "media",
   "blocks": [
    {
     "title": "Ganho",
     "type": "radio",
     "comments": [
      {
       "title": "1. insuficiente",
       "property": "gain",
       "value": "insufficient"
      },
      {
       "title": "2. apropriado",
       "property": "gain",
       "value": "appropriate"
      },
      {
       "title": "3. excessivo",
       "property": "gain",
       "value": "excessive"
      }
     ]
    },
    {
     "title": "Profundidade",
     "type": "radio",
     "comments": [
      {
       "title": "1. insuficiente",
       "property": "depth",
       "value": "insufficient"
      },
      {
       "title": "2. apropriado",
       "property": "depth",
       "value": "appropriate"
      },
      {
       "title": "3. excessivo",
       "property": "depth",
       "value": "excessive"
      }
     ]
    },
    {
     "title": "Nota",
     "type": "radio-h",
     "comments": [
      {
       "title": "1 |",
       "property": "grade",
       "value": "1"
      },
      {
       "title": "2 |",
       "property": "grade",
       "value": "2"
      },
      {
       "title": "3 |",
       "property": "grade",
       "value": "3"
      },
      {
       "title": "4 |",
       "property": "grade",
       "value": "4"
      },
      {
       "title": "5 |",
       "property": "grade",
       "value": "5"
      }
     ]
    },
    {
     "title": "Referências anatómicas/qualidade",
     "type": "checkbox",
     "comments": [
      {
       "title": "Bexiga ausente",
       "property": "bladder",
       "value": "not_present"
      },
      {
       "title": "Próstata/útero ausente",
       "property": "prostate_uterus",
       "value": "not_present"
      }
     ]
    }
   ]
  },
  "AB-PL": {
   "title": "Vídeo - Pelve longitudinal",
   "property": "media",
   "blocks": [
    {
     "title": "Ganho",
     "type": "radio",
     "comments": [
      {
       "title": "1. insuficiente",
       "property": "gain",
       "value": "insufficient"
      },
      {
       "title": "2. apropriado",
       "property": "gain",
       "value": "appropriate"
      },
      {
       "title": "3. excessivo",
       "property": "gain",
       "value": "excessive"
      }
     ]
    },
    {
     "title": "Profundidade",
     "type": "radio",
     "comments": [
      {
       "title": "1. insuficiente",
       "property": "depth",
       "value": "insufficient"
      },
      {
       "title": "2. apropriado",
       "property": "depth",
       "value": "appropriate"
      },
      {
       "title": "3. excessivo",
       "property": "depth",
       "value": "excessive"
      }
     ]
    },
    {
     "title": "Nota",
     "type": "radio-h",
     "comments": [
      {
       "title": "1 |",
       "property": "grade",
       "value": "1"
      },
      {
       "title": "2 |",
       "property": "grade",
       "value": "2"
      },
      {
       "title": "3 |",
       "property": "grade",
       "value": "3"
      },
      {
       "title": "4 |",
       "property": "grade",
       "value": "4"
      },
      {
       "title": "5 |",
       "property": "grade",
       "value": "5"
      }
     ]
    },
    {
     "title": "Referências anatómicas/qualidade",
     "type": "checkbox",
     "comments": [
      {
       "title": "Bexiga ausente",
       "property": "bladder",
       "value": "not_present"
      },
      {
       "title": "Próstata/útero ausente",
       "property": "prostate_uterus",
       "value": "not_present"
      }
     ]
    }
   ]
  }
 }
}